drfpolicy/__init__.py
drfpolicy/permissions.py
drfpolicy/policy.py
drfpolicy/mixins.py
drfpolicy-0.3.0.dist-info/metadata.json
drfpolicy-0.3.0.dist-info/WHEEL
drfpolicy-0.3.0.dist-info/METADATA
drfpolicy-0.3.0.dist-info/DESCRIPTION.rst
drfpolicy-0.3.0.dist-info/RECORD
drfpolicy-0.3.0.dist-info/top_level.txt
